MANIFEST.in
setup.cfg
setup.py
tw2/__init__.py
tw2.recaptcha.egg-info/PKG-INFO
tw2.recaptcha.egg-info/SOURCES.txt
tw2.recaptcha.egg-info/dependency_links.txt
tw2.recaptcha.egg-info/entry_points.txt
tw2.recaptcha.egg-info/namespace_packages.txt
tw2.recaptcha.egg-info/not-zip-safe
tw2.recaptcha.egg-info/requires.txt
tw2.recaptcha.egg-info/top_level.txt
tw2/recaptcha/__init__.py
tw2/recaptcha/release.py
tw2/recaptcha/validator.py
tw2/recaptcha/widgets.py