Metadata-Version: 1.0
Name: tw2.recaptcha
Version: 0.8
Summary: Handy ReCaptcha Widget for tw2
Home-page: http://github.com/toscawidgets/tw2.recaptcha
Author: Christopher Perkins
Author-email: chris@percious.com
License: UNKNOWN
Download-URL: http://toscawidgets.org/download
Platform: UNKNOWN
Classifier: Development Status :: 3 - Alpha
Classifier: Environment :: Web Environment
Classifier: Topic :: Software Development :: Libraries :: Python Modules
Classifier: Topic :: Software Development :: Widget Sets
Classifier: Intended Audience :: Developers
Classifier: Operating System :: OS Independent
Classifier: Programming Language :: Python
